kinto_fxa/__init__.py
kinto_fxa/authentication.py
kinto_fxa/utils.py
kinto_fxa/scripts/__init__.py
kinto_fxa/scripts/__main__.py
kinto_fxa/scripts/process_account_events.py
kinto_fxa/tests/__init__.py
kinto_fxa/tests/test_authentication.py
kinto_fxa/tests/test_includeme.py
kinto_fxa/tests/test_process_account_events.py
kinto_fxa/tests/test_scripts_main.py
kinto_fxa/tests/test_utils.py
kinto_fxa/tests/test_views.py
kinto_fxa/views/__init__.py
kinto_fxa/views/params.py
kinto_fxa/views/relier.py
kinto_fxa-2.5.3.dist-info/DESCRIPTION.rst
kinto_fxa-2.5.3.dist-info/METADATA
kinto_fxa-2.5.3.dist-info/RECORD
kinto_fxa-2.5.3.dist-info/WHEEL
kinto_fxa-2.5.3.dist-info/entry_points.txt
kinto_fxa-2.5.3.dist-info/metadata.json
kinto_fxa-2.5.3.dist-info/top_level.txt
