Metadata-Version: 2.0
Name: kinto-fxa
Version: 2.5.3
Summary: Firefox Accounts support in Kinto
Home-page: https://github.com/Kinto/kinto-fxa
Author: Mozilla Services
Author-email: services-dev@mozilla.com
License: Apache License (2.0)
Keywords: web services
Platform: UNKNOWN
Classifier: Programming Language :: Python
Classifier: Programming Language :: Python :: 3
Classifier: Programming Language :: Python :: 3.5
Classifier: Programming Language :: Python :: 3.6
Classifier: Topic :: Internet :: WWW/HTTP
Classifier: Topic :: Internet :: WWW/HTTP :: WSGI :: Application
Classifier: License :: OSI Approved :: Apache Software License
Requires-Dist: kinto (>=5.0)
Requires-Dist: pyfxa (>=0.0.9)
Provides-Extra: scripts
Requires-Dist: SQLAlchemy; extra == 'scripts'
Requires-Dist: boto3; extra == 'scripts'
Requires-Dist: ec2-metadata; extra == 'scripts'
Requires-Dist: psycopg2 (>2.5); extra == 'scripts'
Requires-Dist: zope.sqlalchemy; extra == 'scripts'
